beamer/__init__.py
beamer/agent.py
beamer/chain.py
beamer/cli.py
beamer/config.py
beamer/contracts.py
beamer/data/abi/StandardToken.json
beamer/data/relayers/relayer-node16-linux-x64
beamer/data/relayers/relayer-node16-macos-x64
beamer/data/tokens-mainnet.json
beamer/data/tokens.example.json
beamer/data/tokens.json
beamer/events.py
beamer/l1_resolution.py
beamer/metrics.py
beamer/models/__init__.py
beamer/models/claim.py
beamer/models/request.py
beamer/state_machine.py
beamer/tests/__init__.py
beamer/tests/agent/__init__.py
beamer/tests/agent/test_challenge.py
beamer/tests/agent/test_cli.py
beamer/tests/agent/test_request.py
beamer/tests/agent/unit/__init__.py
beamer/tests/agent/unit/test_challenge.py
beamer/tests/agent/unit/test_handlers.py
beamer/tests/agent/unit/test_invalidate.py
beamer/tests/agent/unit/test_l1.py
beamer/tests/agent/unit/utils.py
beamer/tests/agent/utils.py
beamer/tests/conftest.py
beamer/tests/constants.py
beamer/tests/contracts/__init__.py
beamer/tests/contracts/test_fill_manager.py
beamer/tests/contracts/test_l1_resolution.py
beamer/tests/contracts/test_request_manager.py
beamer/tests/contracts/test_request_manager_fees.py
beamer/tests/contracts/test_resolution_registry.py
beamer/tests/util.py
beamer/tracker.py
beamer/typing.py
beamer/util.py
beamer_bridge-0.1.0.dist-info/entry_points.txt
beamer_bridge-0.1.0.dist-info/LICENSE
beamer_bridge-0.1.0.dist-info/WHEEL
beamer_bridge-0.1.0.dist-info/METADATA
beamer_bridge-0.1.0.dist-info/RECORD
