Metadata-Version: 2.1
Name: beamer-bridge
Version: 0.1.0
Summary: Bridging rollups with L1 guaranteed security
Home-page: https://www.beamerbridge.com/
License: MIT
Author: Beamer Bridge Team
Author-email: contact@beamerbridge.com
Requires-Python: >=3.9,<3.10
Classifier: License :: OSI Approved :: MIT License
Classifier: Programming Language :: Python :: 3
Classifier: Programming Language :: Python :: 3.9
Requires-Dist: click (>=8.0.3,<9.0.0)
Requires-Dist: prometheus-client (>=0.14.1,<0.15.0)
Requires-Dist: python-statemachine (>=0.8.0,<0.9.0)
Requires-Dist: structlog (>=21.5.0,<22.0.0)
Requires-Dist: web3 (>=5.24.0,<6.0.0)
Project-URL: Documentation, https://docs.beamerbridge.com/
Project-URL: Repository, https://github.com/beamer-bridge/beamer
